pytest_param_files/__init__.py
pytest_param_files/main.py
pytest_param_files-0.6.0.dist-info/entry_points.txt
pytest_param_files-0.6.0.dist-info/LICENSE
pytest_param_files-0.6.0.dist-info/WHEEL
pytest_param_files-0.6.0.dist-info/METADATA
pytest_param_files-0.6.0.dist-info/RECORD
