Metadata-Version: 2.1
Name: pytest_param_files
Version: 0.6.0
Summary: Create pytest parametrize decorators from external files.
Keywords: pytest,parameterized
Author-email: Chris Sewell <chrisj_sewell@hotmail.com>
Requires-Python: >=3.8
Classifier: License :: OSI Approved :: MIT License
Classifier: Programming Language :: Python :: 3
Classifier: Programming Language :: Python :: 3.8
Classifier: Programming Language :: Python :: 3.9
Classifier: Programming Language :: Python :: 3.10
Classifier: Programming Language :: Python :: 3.11
Classifier: Framework :: Pytest
Requires-Dist: pytest
Requires-Dist: ruamel.yaml>=0.15
Requires-Dist: pytest-cov ; extra == "codecov"
Project-URL: Home, https://github.com/chrisjsewell/pytest-param-files
Provides-Extra: codecov
